README.txt
setup.cfg
setup.py
Coveralls_HG.egg-info/PKG-INFO
Coveralls_HG.egg-info/SOURCES.txt
Coveralls_HG.egg-info/dependency_links.txt
Coveralls_HG.egg-info/entry_points.txt
Coveralls_HG.egg-info/requires.txt
Coveralls_HG.egg-info/top_level.txt
coveralls_hg/__init__.py
coveralls_hg/api.py