Metadata-Version: 1.1
Name: Coveralls-HG
Version: 2.0.0.2
Summary: Coveralls API for: Python 3+, Coverage & Mercurial.
Home-page: https://bitbucket.org/hellwig/Coveralls-HG/
Author: Martin P. Hellwig
Author-email: martin.hellwig@gmail.com
License: BSD
Download-URL: https://bitbucket.org/hellwig/Coveralls-HG/get/91cc6c3696beb70eb52b85d9eb33c0dfc0dc557f.zip
Keywords: Coveralls,Codeship,BitBucket
Platform: UNKNOWN
Classifier: Programming Language :: Python :: 3
